{
  "schema": "neoview.report.v1",
  "source_report_id": "manual-43a7b5a9-cdd2-4bc0-8b29-fee0ef86954b",
  "report_status": "approved",
  "report": {
    "name": "Relatório teste",
    "description": "É um teste",
    "date": "2026-03-14",
    "size_label": "",
    "size_bytes": 0,
    "url": null
  },
  "hierarchy": {
    "company": {
      "id": "coelba",
      "name": "Neoenergia Coelba"
    },
    "superintendence": {
      "id": "sup-relacionamento-clientes",
      "name": "Superintendência de Relacionamento com Clientes"
    },
    "management": {
      "id": "ger-receita",
      "name": "Gerência da Gestão da Receita"
    },
    "project": {
      "id": "uni-recuperacao-credito",
      "name": "Unidade de Recuperação de Crédito"
    }
  },
  "indicators": [
    {
      "id": "",
      "name": "GAB",
      "value": "",
      "unit": "",
      "trend": ""
    },
    {
      "id": "",
      "name": "JAO",
      "value": "",
      "unit": "",
      "trend": ""
    }
  ],
  "metrics": {
    "views": 1,
    "comments": 0,
    "likes": 0,
    "shares": 0
  },
  "path": [
    "Neoenergia Coelba",
    "Superintendência de Relacionamento com Clientes",
    "Gerência da Gestão da Receita",
    "Unidade de Recuperação de Crédito",
    "Relatório teste"
  ],
  "raw_json": {
    "schema": "neoview.report.v1",
    "source_report_id": "manual-43a7b5a9-cdd2-4bc0-8b29-fee0ef86954b",
    "report_status": "approved",
    "report": {
      "name": "Relatório teste",
      "description": "É um teste",
      "date": "2026-03-14",
      "size_label": "",
      "size_bytes": 0,
      "url": null
    },
    "hierarchy": {
      "company": {
        "id": "coelba",
        "name": "Neoenergia Coelba"
      },
      "superintendence": {
        "id": "sup-relacionamento-clientes",
        "name": "Superintendência de Relacionamento com Clientes"
      },
      "management": {
        "id": "ger-receita",
        "name": "Gerência da Gestão da Receita"
      },
      "project": {
        "id": "uni-recuperacao-credito",
        "name": "Unidade de Recuperação de Crédito"
      }
    },
    "indicators": [
      {
        "id": "",
        "name": "GAB",
        "value": "",
        "unit": "",
        "trend": ""
      },
      {
        "id": "",
        "name": "JAO",
        "value": "",
        "unit": "",
        "trend": ""
      }
    ],
    "metrics": {
      "views": 1,
      "comments": 0,
      "likes": 0,
      "shares": 0
    },
    "path": [
      "Neoenergia Coelba",
      "Superintendência de Relacionamento com Clientes",
      "Gerência da Gestão da Receita",
      "Unidade de Recuperação de Crédito",
      "Relatório teste"
    ],
    "raw_json": {
      "schema": "neoview.report.v1",
      "source_report_id": "manual-43a7b5a9-cdd2-4bc0-8b29-fee0ef86954b",
      "report_status": "approved",
      "report": {
        "name": "Relatório teste",
        "description": "É um teste",
        "date": "2026-03-14",
        "size_label": "",
        "size_bytes": 0,
        "url": null
      },
      "hierarchy": {
        "company": {
          "id": "coelba",
          "name": "Neoenergia Coelba"
        },
        "superintendence": {
          "id": "sup-relacionamento-clientes",
          "name": "Superintendência de Relacionamento com Clientes"
        },
        "management": {
          "id": "ger-receita",
          "name": "Gerência da Gestão da Receita"
        },
        "project": {
          "id": "uni-recuperacao-credito",
          "name": "Unidade de Recuperação de Crédito"
        }
      },
      "indicators": [
        {
          "id": "",
          "name": "GAB",
          "value": "",
          "unit": "",
          "trend": ""
        },
        {
          "id": "",
          "name": "JAO",
          "value": "",
          "unit": "",
          "trend": ""
        }
      ],
      "metrics": {
        "views": 1,
        "comments": 0,
        "likes": 0,
        "shares": 0
      },
      "path": [
        "Neoenergia Coelba",
        "Superintendência de Relacionamento com Clientes",
        "Gerência da Gestão da Receita",
        "Unidade de Recuperação de Crédito",
        "Relatório teste"
      ],
      "raw_json": {
        "schema": "neoview.report.v1",
        "source_report_id": "manual-43a7b5a9-cdd2-4bc0-8b29-fee0ef86954b",
        "report_status": "approved",
        "report": {
          "name": "Relatório teste",
          "description": "É um teste",
          "date": "2026-03-14",
          "size_label": "",
          "size_bytes": 0,
          "url": null
        },
        "hierarchy": {
          "company": {
            "id": "coelba",
            "name": "Neoenergia Coelba"
          },
          "superintendence": {
            "id": "sup-relacionamento-clientes",
            "name": "Superintendência de Relacionamento com Clientes"
          },
          "management": {
            "id": "ger-receita",
            "name": "Gerência da Gestão da Receita"
          },
          "project": {
            "id": "uni-recuperacao-credito",
            "name": "Unidade de Recuperação de Crédito"
          }
        },
        "indicators": [
          {
            "id": "",
            "name": "GAB",
            "value": "",
            "unit": "",
            "trend": ""
          },
          {
            "id": "",
            "name": "JAO",
            "value": "",
            "unit": "",
            "trend": ""
          }
        ],
        "metrics": {
          "views": 1,
          "comments": 0,
          "likes": 0,
          "shares": 0
        },
        "path": [
          "Neoenergia Coelba",
          "Superintendência de Relacionamento com Clientes",
          "Gerência da Gestão da Receita",
          "Unidade de Recuperação de Crédito",
          "Relatório teste"
        ],
        "raw_json": {
          "schema": "neoview.report.v1",
          "source_report_id": "manual-43a7b5a9-cdd2-4bc0-8b29-fee0ef86954b",
          "report_status": "approved",
          "report": {
            "name": "Relatório teste",
            "description": "É um teste",
            "date": "2026-03-14",
            "size_label": "",
            "size_bytes": 0,
            "url": null
          },
          "hierarchy": {
            "company": {
              "id": "coelba",
              "name": "Neoenergia Coelba"
            },
            "superintendence": {
              "id": "sup-relacionamento-clientes",
              "name": "Superintendência de Relacionamento com Clientes"
            },
            "management": {
              "id": "ger-receita",
              "name": "Gerência da Gestão da Receita"
            },
            "project": {
              "id": "uni-recuperacao-credito",
              "name": "Unidade de Recuperação de Crédito"
            }
          },
          "indicators": [
            {
              "id": "",
              "name": "GAB",
              "value": "",
              "unit": "",
              "trend": ""
            },
            {
              "id": "",
              "name": "JAO",
              "value": "",
              "unit": "",
              "trend": ""
            }
          ],
          "metrics": {
            "views": 1,
            "comments": 0,
            "likes": 0,
            "shares": 0
          },
          "path": [
            "Neoenergia Coelba",
            "Superintendência de Relacionamento com Clientes",
            "Gerência da Gestão da Receita",
            "Unidade de Recuperação de Crédito",
            "Relatório teste"
          ],
          "raw_json": {
            "schema": "neoview.report.v1",
            "source_report_id": "manual-43a7b5a9-cdd2-4bc0-8b29-fee0ef86954b",
            "report_status": "approved",
            "report": {
              "name": "Relatório teste",
              "description": "É um teste",
              "date": "2026-03-14",
              "size_label": "",
              "size_bytes": 0,
              "url": null
            },
            "hierarchy": {
              "company": {
                "id": "coelba",
                "name": "Neoenergia Coelba"
              },
              "superintendence": {
                "id": "sup-relacionamento-clientes",
                "name": "Superintendência de Relacionamento com Clientes"
              },
              "management": {
                "id": "ger-receita",
                "name": "Gerência da Gestão da Receita"
              },
              "project": {
                "id": "uni-recuperacao-credito",
                "name": "Unidade de Recuperação de Crédito"
              }
            },
            "indicators": [
              {
                "id": "",
                "name": "GAB",
                "value": "",
                "unit": "",
                "trend": ""
              },
              {
                "id": "",
                "name": "JAO",
                "value": "",
                "unit": "",
                "trend": ""
              }
            ],
            "metrics": {
              "views": 1,
              "comments": 0,
              "likes": 0,
              "shares": 0
            },
            "path": [
              "Neoenergia Coelba",
              "Superintendência de Relacionamento com Clientes",
              "Gerência da Gestão da Receita",
              "Unidade de Recuperação de Crédito",
              "Relatório teste"
            ],
            "raw_json": {
              "schema": "neoview.report.v1",
              "source_report_id": "manual-43a7b5a9-cdd2-4bc0-8b29-fee0ef86954b",
              "report_status": "approved",
              "report": {
                "name": "Relatório teste",
                "description": "É um teste",
                "date": "2026-03-14",
                "size_label": "",
                "size_bytes": 0,
                "url": null
              },
              "hierarchy": {
                "company": {
                  "id": "coelba",
                  "name": "Neoenergia Coelba"
                },
                "superintendence": {
                  "id": "sup-relacionamento-clientes",
                  "name": "Superintendência de Relacionamento com Clientes"
                },
                "management": {
                  "id": "ger-receita",
                  "name": "Gerência da Gestão da Receita"
                },
                "project": {
                  "id": "uni-recuperacao-credito",
                  "name": "Unidade de Recuperação de Crédito"
                }
              },
              "indicators": [
                {
                  "id": "",
                  "name": "GAB",
                  "value": "",
                  "unit": "",
                  "trend": ""
                },
                {
                  "id": "",
                  "name": "JAO",
                  "value": "",
                  "unit": "",
                  "trend": ""
                }
              ],
              "metrics": {
                "views": 1,
                "comments": 0,
                "likes": 0,
                "shares": 0
              },
              "path": [
                "Neoenergia Coelba",
                "Superintendência de Relacionamento com Clientes",
                "Gerência da Gestão da Receita",
                "Unidade de Recuperação de Crédito",
                "Relatório teste"
              ],
              "raw_json": {
                "schema": "neoview.report.v1",
                "source_report_id": "manual-43a7b5a9-cdd2-4bc0-8b29-fee0ef86954b",
                "report_status": "approved",
                "report": {
                  "name": "Relatório teste",
                  "description": "É um teste",
                  "date": "2026-03-14",
                  "size_label": "",
                  "size_bytes": 0,
                  "url": null
                },
                "hierarchy": {
                  "company": {
                    "id": "coelba",
                    "name": "Neoenergia Coelba"
                  },
                  "superintendence": {
                    "id": "sup-relacionamento-clientes",
                    "name": "Superintendência de Relacionamento com Clientes"
                  },
                  "management": {
                    "id": "ger-receita",
                    "name": "Gerência da Gestão da Receita"
                  },
                  "project": {
                    "id": "uni-recuperacao-credito",
                    "name": "Unidade de Recuperação de Crédito"
                  }
                },
                "indicators": [
                  {
                    "id": "",
                    "name": "GAB",
                    "value": "",
                    "unit": "",
                    "trend": ""
                  },
                  {
                    "id": "",
                    "name": "JAO",
                    "value": "",
                    "unit": "",
                    "trend": ""
                  }
                ],
                "metrics": {
                  "views": 1,
                  "comments": 0,
                  "likes": 0,
                  "shares": 0
                },
                "path": [
                  "Neoenergia Coelba",
                  "Superintendência de Relacionamento com Clientes",
                  "Gerência da Gestão da Receita",
                  "Unidade de Recuperação de Crédito",
                  "Relatório teste"
                ],
                "raw_json": {
                  "schema": "neoview.report.v1",
                  "source_report_id": "manual-43a7b5a9-cdd2-4bc0-8b29-fee0ef86954b",
                  "report_status": "approved",
                  "report": {
                    "name": "Relatório teste",
                    "description": "É um teste",
                    "date": "2026-03-14",
                    "size_label": "",
                    "size_bytes": 0,
                    "url": null
                  },
                  "hierarchy": {
                    "company": {
                      "id": "coelba",
                      "name": "Neoenergia Coelba"
                    },
                    "superintendence": {
                      "id": "sup-relacionamento-clientes",
                      "name": "Superintendência de Relacionamento com Clientes"
                    },
                    "management": {
                      "id": "ger-receita",
                      "name": "Gerência da Gestão da Receita"
                    },
                    "project": {
                      "id": "uni-recuperacao-credito",
                      "name": "Unidade de Recuperação de Crédito"
                    }
                  },
                  "indicators": [
                    {
                      "id": "",
                      "name": "GAB",
                      "value": "",
                      "unit": "",
                      "trend": ""
                    },
                    {
                      "id": "",
                      "name": "JAO",
                      "value": "",
                      "unit": "",
                      "trend": ""
                    }
                  ],
                  "metrics": {
                    "views": 1,
                    "comments": 0,
                    "likes": 0,
                    "shares": 0
                  },
                  "path": [
                    "Neoenergia Coelba",
                    "Superintendência de Relacionamento com Clientes",
                    "Gerência da Gestão da Receita",
                    "Unidade de Recuperação de Crédito",
                    "Relatório teste"
                  ],
                  "raw_json": {
                    "schema": "neoview.report.v1",
                    "source_report_id": "manual-43a7b5a9-cdd2-4bc0-8b29-fee0ef86954b",
                    "report_status": "approved",
                    "report": {
                      "name": "Relatório teste",
                      "description": "É um teste",
                      "date": "2026-03-14",
                      "size_label": "",
                      "size_bytes": 0,
                      "url": null
                    },
                    "hierarchy": {
                      "company": {
                        "id": "coelba",
                        "name": "Neoenergia Coelba"
                      },
                      "superintendence": {
                        "id": "sup-relacionamento-clientes",
                        "name": "Superintendência de Relacionamento com Clientes"
                      },
                      "management": {
                        "id": "ger-receita",
                        "name": "Gerência da Gestão da Receita"
                      },
                      "project": {
                        "id": "uni-recuperacao-credito",
                        "name": "Unidade de Recuperação de Crédito"
                      }
                    },
                    "indicators": [
                      {
                        "id": "",
                        "name": "GAB",
                        "value": "",
                        "unit": "",
                        "trend": ""
                      },
                      {
                        "id": "",
                        "name": "JAO",
                        "value": "",
                        "unit": "",
                        "trend": ""
                      }
                    ],
                    "metrics": {
                      "views": 1,
                      "comments": 0,
                      "likes": 0,
                      "shares": 0
                    },
                    "path": [
                      "Neoenergia Coelba",
                      "Superintendência de Relacionamento com Clientes",
                      "Gerência da Gestão da Receita",
                      "Unidade de Recuperação de Crédito",
                      "Relatório teste"
                    ],
                    "raw_json": {
                      "schema": "neoview.report.v1",
                      "source_report_id": "manual-43a7b5a9-cdd2-4bc0-8b29-fee0ef86954b",
                      "report_status": "approved",
                      "report": {
                        "name": "Relatório teste",
                        "description": "É um teste",
                        "date": "2026-03-14",
                        "size_label": "",
                        "size_bytes": 0,
                        "url": null
                      },
                      "hierarchy": {
                        "company": {
                          "id": "coelba",
                          "name": "Neoenergia Coelba"
                        },
                        "superintendence": {
                          "id": "sup-relacionamento-clientes",
                          "name": "Superintendência de Relacionamento com Clientes"
                        },
                        "management": {
                          "id": "ger-receita",
                          "name": "Gerência da Gestão da Receita"
                        },
                        "project": {
                          "id": "uni-recuperacao-credito",
                          "name": "Unidade de Recuperação de Crédito"
                        }
                      },
                      "indicators": [
                        {
                          "id": "",
                          "name": "GAB",
                          "value": "",
                          "unit": "",
                          "trend": ""
                        },
                        {
                          "id": "",
                          "name": "JAO",
                          "value": "",
                          "unit": "",
                          "trend": ""
                        }
                      ],
                      "metrics": {
                        "views": 1,
                        "comments": 0,
                        "likes": 0,
                        "shares": 0
                      },
                      "path": [
                        "Neoenergia Coelba",
                        "Superintendência de Relacionamento com Clientes",
                        "Gerência da Gestão da Receita",
                        "Unidade de Recuperação de Crédito",
                        "Relatório teste"
                      ],
                      "raw_json": {
                        "schema": "neoview.report.v1",
                        "source_report_id": "manual-43a7b5a9-cdd2-4bc0-8b29-fee0ef86954b",
                        "report_status": "approved",
                        "report": {
                          "name": "Relatório teste",
                          "description": "É um teste",
                          "date": "2026-03-14",
                          "size_label": "",
                          "size_bytes": 0,
                          "url": null
                        },
                        "hierarchy": {
                          "company": {
                            "id": "coelba",
                            "name": "Neoenergia Coelba"
                          },
                          "superintendence": {
                            "id": "sup-relacionamento-clientes",
                            "name": "Superintendência de Relacionamento com Clientes"
                          },
                          "management": {
                            "id": "ger-receita",
                            "name": "Gerência da Gestão da Receita"
                          },
                          "project": {
                            "id": "uni-recuperacao-credito",
                            "name": "Unidade de Recuperação de Crédito"
                          }
                        },
                        "indicators": [
                          {
                            "id": "",
                            "name": "GAB",
                            "value": "",
                            "unit": "",
                            "trend": ""
                          },
                          {
                            "id": "",
                            "name": "JAO",
                            "value": "",
                            "unit": "",
                            "trend": ""
                          }
                        ],
                        "metrics": {
                          "views": 1,
                          "comments": 0,
                          "likes": 0,
                          "shares": 0
                        },
                        "path": [
                          "Neoenergia Coelba",
                          "Superintendência de Relacionamento com Clientes",
                          "Gerência da Gestão da Receita",
                          "Unidade de Recuperação de Crédito",
                          "Relatório teste"
                        ],
                        "raw_json": {
                          "schema": "neoview.report.v1",
                          "source_report_id": "manual-43a7b5a9-cdd2-4bc0-8b29-fee0ef86954b",
                          "report_status": "approved",
                          "report": {
                            "name": "Relatório teste",
                            "description": "É um teste",
                            "date": "2026-03-14",
                            "size_label": "",
                            "size_bytes": 0,
                            "url": null
                          },
                          "hierarchy": {
                            "company": {
                              "id": "coelba",
                              "name": "Neoenergia Coelba"
                            },
                            "superintendence": {
                              "id": "sup-relacionamento-clientes",
                              "name": "Superintendência de Relacionamento com Clientes"
                            },
                            "management": {
                              "id": "ger-receita",
                              "name": "Gerência da Gestão da Receita"
                            },
                            "project": {
                              "id": "uni-recuperacao-credito",
                              "name": "Unidade de Recuperação de Crédito"
                            }
                          },
                          "indicators": [
                            {
                              "id": "",
                              "name": "GAB",
                              "value": "",
                              "unit": "",
                              "trend": ""
                            },
                            {
                              "id": "",
                              "name": "JAO",
                              "value": "",
                              "unit": "",
                              "trend": ""
                            }
                          ],
                          "metrics": {
                            "views": 1,
                            "comments": 0,
                            "likes": 0,
                            "shares": 0
                          },
                          "path": [
                            "Neoenergia Coelba",
                            "Superintendência de Relacionamento com Clientes",
                            "Gerência da Gestão da Receita",
                            "Unidade de Recuperação de Crédito",
                            "Relatório teste"
                          ],
                          "raw_json": {
                            "schema": "neoview.report.v1",
                            "source_report_id": "manual-43a7b5a9-cdd2-4bc0-8b29-fee0ef86954b",
                            "report_status": "approved",
                            "report": {
                              "name": "Relatório teste",
                              "description": "É um teste",
                              "date": "2026-03-14",
                              "size_label": "",
                              "size_bytes": 0,
                              "url": null
                            },
                            "hierarchy": {
                              "company": {
                                "id": "coelba",
                                "name": "Neoenergia Coelba"
                              },
                              "superintendence": {
                                "id": "sup-relacionamento-clientes",
                                "name": "Superintendência de Relacionamento com Clientes"
                              },
                              "management": {
                                "id": "ger-receita",
                                "name": "Gerência da Gestão da Receita"
                              },
                              "project": {
                                "id": "uni-recuperacao-credito",
                                "name": "Unidade de Recuperação de Crédito"
                              }
                            },
                            "indicators": [
                              {
                                "id": "",
                                "name": "GAB",
                                "value": "",
                                "unit": "",
                                "trend": ""
                              },
                              {
                                "id": "",
                                "name": "JAO",
                                "value": "",
                                "unit": "",
                                "trend": ""
                              }
                            ],
                            "metrics": {
                              "views": 1,
                              "comments": 0,
                              "likes": 0,
                              "shares": 0
                            },
                            "path": [
                              "Neoenergia Coelba",
                              "Superintendência de Relacionamento com Clientes",
                              "Gerência da Gestão da Receita",
                              "Unidade de Recuperação de Crédito",
                              "Relatório teste"
                            ],
                            "raw_json": {
                              "schema": "neoview.report.v1",
                              "source_report_id": "manual-43a7b5a9-cdd2-4bc0-8b29-fee0ef86954b",
                              "report_status": "approved",
                              "report": {
                                "name": "Relatório teste",
                                "description": "É um teste",
                                "date": "2026-03-14",
                                "size_label": "",
                                "size_bytes": 0,
                                "url": null
                              },
                              "hierarchy": {
                                "company": {
                                  "id": "coelba",
                                  "name": "Neoenergia Coelba"
                                },
                                "superintendence": {
                                  "id": "sup-relacionamento-clientes",
                                  "name": "Superintendência de Relacionamento com Clientes"
                                },
                                "management": {
                                  "id": "ger-receita",
                                  "name": "Gerência da Gestão da Receita"
                                },
                                "project": {
                                  "id": "uni-recuperacao-credito",
                                  "name": "Unidade de Recuperação de Crédito"
                                }
                              },
                              "indicators": [
                                {
                                  "id": "",
                                  "name": "GAB",
                                  "value": "",
                                  "unit": "",
                                  "trend": ""
                                },
                                {
                                  "id": "",
                                  "name": "JAO",
                                  "value": "",
                                  "unit": "",
                                  "trend": ""
                                }
                              ],
                              "metrics": {
                                "views": 1,
                                "comments": 0,
                                "likes": 0,
                                "shares": 0
                              },
                              "path": [
                                "Neoenergia Coelba",
                                "Superintendência de Relacionamento com Clientes",
                                "Gerência da Gestão da Receita",
                                "Unidade de Recuperação de Crédito",
                                "Relatório teste"
                              ],
                              "raw_json": {
                                "schema": "neoview.report.v1",
                                "source_report_id": "manual-43a7b5a9-cdd2-4bc0-8b29-fee0ef86954b",
                                "report_status": "approved",
                                "report": {
                                  "name": "Relatório teste",
                                  "description": "É um teste",
                                  "date": "2026-03-14T03:00:00.000Z",
                                  "size_label": "",
                                  "size_bytes": "0",
                                  "url": "https://1drv.ms/w/c/668609ce6f1faa08/IQCnrxbQsWWsTKz5ahR4Mkc_ARMrV0e2DpFPOsTUW3J1TpU?e=jhO0NA"
                                },
                                "hierarchy": {
                                  "company": {
                                    "id": "coelba",
                                    "name": "Neoenergia Coelba"
                                  },
                                  "superintendence": {
                                    "id": "sup-relacionamento-clientes",
                                    "name": "Superintendência de Relacionamento com Clientes"
                                  },
                                  "management": {
                                    "id": "ger-receita",
                                    "name": "Gerência da Gestão da Receita"
                                  },
                                  "project": {
                                    "id": "uni-recuperacao-credito",
                                    "name": "Unidade de Recuperação de Crédito"
                                  }
                                },
                                "indicators": [
                                  {
                                    "id": "",
                                    "name": "GAB",
                                    "value": "",
                                    "unit": "",
                                    "trend": "stable"
                                  },
                                  {
                                    "id": "",
                                    "name": "JAO",
                                    "value": "",
                                    "unit": "",
                                    "trend": "stable"
                                  }
                                ],
                                "metrics": {
                                  "views": 0,
                                  "comments": 0,
                                  "likes": 0,
                                  "shares": 0
                                },
                                "path": [
                                  "Neoenergia Coelba",
                                  "Superintendência de Relacionamento com Clientes",
                                  "Gerência da Gestão da Receita",
                                  "Unidade de Recuperação de Crédito",
                                  "Relatório teste"
                                ],
                                "raw_json": {
                                  "metrics": {
                                    "likes": 0,
                                    "views": 0,
                                    "shares": 0,
                                    "comments": 0
                                  },
                                  "assetType": "hyperlink",
                                  "companyId": "coelba",
                                  "projectId": "uni-recuperacao-credito",
                                  "reportUrl": "https://1drv.ms/w/c/668609ce6f1faa08/IQCnrxbQsWWsTKz5ahR4Mkc_ARMrV0e2DpFPOsTUW3J1TpU?e=jhO0NA",
                                  "indicators": [
                                    {
                                      "name": "GAB"
                                    },
                                    {
                                      "name": "JAO"
                                    }
                                  ],
                                  "reportDate": "2026-03-14",
                                  "reportName": "Relatório teste",
                                  "companyName": "Neoenergia Coelba",
                                  "projectName": "Unidade de Recuperação de Crédito",
                                  "managementId": "ger-receita",
                                  "managementName": "Gerência da Gestão da Receita",
                                  "reportSizeLabel": "",
                                  "submittedByName": "Teste",
                                  "submittedByEmail": "teste@neoenergia.com",
                                  "reportDescription": "É um teste",
                                  "superintendenceId": "sup-relacionamento-clientes",
                                  "superintendenceName": "Superintendência de Relacionamento com Clientes"
                                },
                                "generated_at": "2026-03-14T19:27:35.080Z"
                              },
                              "generated_at": "2026-03-31T23:04:36.403Z"
                            },
                            "generated_at": "2026-03-31T23:07:12.345Z"
                          },
                          "generated_at": "2026-03-31T23:34:15.243Z"
                        },
                        "generated_at": "2026-03-31T23:36:58.366Z"
                      },
                      "generated_at": "2026-03-31T23:56:53.915Z"
                    },
                    "generated_at": "2026-04-01T07:33:53.299Z"
                  },
                  "generated_at": "2026-04-01T08:05:22.686Z"
                },
                "generated_at": "2026-04-01T08:09:39.963Z"
              },
              "generated_at": "2026-04-03T13:57:26.437Z"
            },
            "generated_at": "2026-04-03T14:03:37.448Z"
          },
          "generated_at": "2026-04-03T14:08:34.473Z"
        },
        "generated_at": "2026-04-03T14:42:07.400Z"
      },
      "generated_at": "2026-04-03T14:44:31.028Z"
    },
    "generated_at": "2026-04-03T14:58:40.253Z"
  },
  "generated_at": "2026-06-05T22:06:43.660Z"
}